dqdata/__init__.py
dqdata/api_client.py
dqdata/blp_utils.py
dqdata/db_client.py
dqdata/file_order.py
dqdata/sim_trader.py
dqdata/utils.py
dqdata/wind_adapter_utils.py
dqdata/wind_request.py
dqdata/wind_utils.py
dqdata-0.3.16.dist-info/LICENSE
dqdata-0.3.16.dist-info/METADATA
dqdata-0.3.16.dist-info/WHEEL
dqdata-0.3.16.dist-info/top_level.txt
dqdata-0.3.16.dist-info/RECORD
