Metadata-Version: 2.1
Name: dqdata
Version: 0.3.16
Summary: Data sdk for DuCheng quant database.
Home-page: https://pypi.org/project/dqdata/
Author: duchengdev
Author-email: dev@shducheng.com.cn
Project-URL: Bug Tracker, https://pypi.org/project/dqdata/
Classifier: Programming Language :: Python :: 3
Classifier: License :: OSI Approved :: MIT License
Classifier: Operating System :: OS Independent
Requires-Python: >=3.7
License-File: LICENSE
Requires-Dist: numpy
Requires-Dist: pandas
Requires-Dist: urllib3
Requires-Dist: requests
Requires-Dist: logbook
Requires-Dist: schedule
Requires-Dist: watchdog
Requires-Dist: sqlalchemy
Requires-Dist: xbbg
